{"cameraMode":{"drawMode":0,"name":"Shaded","section":"Shading Mode"},"sceneLighting":false,"audioPlay":false,"sceneViewState":{"showFog":true,"showMaterialUpdate":false,"showSkybox":false,"showFlares":true,"showImageEffects":true,"showParticleSystems":true},"in2DMode":false,"pivot":{"x":90.0257568359375,"y":-7.099846839904785,"z":46.19660949707031},"rotation":{"x":0.32450491189956667,"y":-0.22594793140888215,"z":0.08013342320919037,"w":0.9149987697601318},"size":0.5715708136558533,"orthographic":false}